c_gae.cpython-312-x86_64-linux-gnu.so
pufferlib/pytorch.py
pufferlib/utils.py
pufferlib/version.py
pufferlib/models.py
pufferlib/spaces.py
pufferlib/namespace.py
pufferlib/policy_store.py
pufferlib/exceptions.py
pufferlib/puffernet.h
pufferlib/wrappers.py
pufferlib/extensions.pyx
pufferlib/emulation.py
pufferlib/policy_ranker.py
pufferlib/environment.py
pufferlib/puffernet.cpython-312-x86_64-linux-gnu.so
pufferlib/postprocess.py
pufferlib/puffernet.pyx
pufferlib/cleanrl.py
pufferlib/puffernet.c
pufferlib/extensions.cpython-312-x86_64-linux-gnu.so
pufferlib/extensions.c
pufferlib/vector.py
pufferlib/__init__.py
pufferlib/environments/__init__.py
pufferlib/environments/gpudrive/environment.py
pufferlib/environments/gpudrive/torch.py
pufferlib/environments/gpudrive/__init__.py
pufferlib/environments/pokemon_red/environment.py
pufferlib/environments/pokemon_red/torch.py
pufferlib/environments/pokemon_red/__init__.py
pufferlib/environments/minihack/environment.py
pufferlib/environments/minihack/torch.py
pufferlib/environments/minihack/__init__.py
pufferlib/environments/magent/environment.py
pufferlib/environments/magent/torch.py
pufferlib/environments/magent/__init__.py
pufferlib/environments/box2d/environment.py
pufferlib/environments/box2d/torch.py
pufferlib/environments/box2d/__init__.py
pufferlib/environments/slimevolley/environment.py
pufferlib/environments/slimevolley/torch.py
pufferlib/environments/slimevolley/__init__.py
pufferlib/environments/smac/environment.py
pufferlib/environments/smac/torch.py
pufferlib/environments/smac/__init__.py
pufferlib/environments/stable_retro/environment.py
pufferlib/environments/stable_retro/torch.py
pufferlib/environments/stable_retro/__init__.py
pufferlib/environments/nmmo/environment.py
pufferlib/environments/nmmo/torch.py
pufferlib/environments/nmmo/__init__.py
pufferlib/environments/microrts/environment.py
pufferlib/environments/microrts/torch.py
pufferlib-2.0.2.dist-info/METADATA
pufferlib-2.0.2.dist-info/top_level.txt
pufferlib-2.0.2.dist-info/RECORD
pufferlib-2.0.2.dist-info/WHEEL
pufferlib-2.0.2.dist-info/LICENSE
